{
  "id": "4qEixipsxSf1HUubdvnb8zpswKssGnAt3k7kQUnyENrZiV3ZZpoqx9ujTK5RLScB62",
  "title": "exaroth/i3-news",
  "displayTitle": "exaroth/i3-news",
  "url": "https://gh-issues-to-rss.fly.dev/exaroth/i3-news",
  "feedLink": "https://github.com/exaroth/i3-news",
  "isQuery": false,
  "isEmpty": false,
  "isHidden": false,
  "itemCount": 18,
  "items": [
    {
      "title": "[pr-closed]: 0.4.2",
      "url": "https://github.com/exaroth/i3-news/pull/9",
      "date": 1758741001,
      "author": "exaroth",
      "guid": 21395,
      "unread": true,
      "content": "",
      "contentLength": 0,
      "flags": null,
      "enclosureUrl": "",
      "enclosureMime": "",
      "commentsUrl": null
    },
    {
      "title": "[pr-open]: 0.4.2",
      "url": "https://github.com/exaroth/i3-news/pull/9",
      "date": 1758740856,
      "author": "exaroth",
      "guid": 21394,
      "unread": true,
      "content": "",
      "contentLength": 0,
      "flags": null,
      "enclosureUrl": "",
      "enclosureMime": "",
      "commentsUrl": null
    },
    {
      "title": "[pr-closed]: 0.4.1",
      "url": "https://github.com/exaroth/i3-news/pull/8",
      "date": 1758690065,
      "author": "exaroth",
      "guid": 21171,
      "unread": true,
      "content": "",
      "contentLength": 0,
      "flags": null,
      "enclosureUrl": "",
      "enclosureMime": "",
      "commentsUrl": null
    },
    {
      "title": "[pr-open]: 0.4.1",
      "url": "https://github.com/exaroth/i3-news/pull/8",
      "date": 1758689870,
      "author": "exaroth",
      "guid": 21170,
      "unread": true,
      "content": "",
      "contentLength": 0,
      "flags": null,
      "enclosureUrl": "",
      "enclosureMime": "",
      "commentsUrl": null
    },
    {
      "title": "[pr-closed]: 0.4.0",
      "url": "https://github.com/exaroth/i3-news/pull/7",
      "date": 1758647272,
      "author": "exaroth",
      "guid": 21068,
      "unread": true,
      "content": "",
      "contentLength": 0,
      "flags": null,
      "enclosureUrl": "",
      "enclosureMime": "",
      "commentsUrl": null
    },
    {
      "title": "[pr-open]: 0.4.0",
      "url": "https://github.com/exaroth/i3-news/pull/7",
      "date": 1758642846,
      "author": "exaroth",
      "guid": 21067,
      "unread": true,
      "content": "",
      "contentLength": 0,
      "flags": null,
      "enclosureUrl": "",
      "enclosureMime": "",
      "commentsUrl": null
    },
    {
      "title": "[pr-closed]: Feat/continuous scroll",
      "url": "https://github.com/exaroth/i3-news/pull/6",
      "date": 1758593807,
      "author": "exaroth",
      "guid": 20871,
      "unread": true,
      "content": "",
      "contentLength": 0,
      "flags": null,
      "enclosureUrl": "",
      "enclosureMime": "",
      "commentsUrl": null
    },
    {
      "title": "[pr-open]: Feat/continuous scroll",
      "url": "https://github.com/exaroth/i3-news/pull/6",
      "date": 1758561293,
      "author": "exaroth",
      "guid": 20752,
      "unread": true,
      "content": "",
      "contentLength": 0,
      "flags": null,
      "enclosureUrl": "",
      "enclosureMime": "",
      "commentsUrl": null
    },
    {
      "title": "[pr-closed]: 0.3.2",
      "url": "https://github.com/exaroth/i3-news/pull/5",
      "date": 1758214743,
      "author": "exaroth",
      "guid": 20033,
      "unread": true,
      "content": "",
      "contentLength": 0,
      "flags": null,
      "enclosureUrl": "",
      "enclosureMime": "",
      "commentsUrl": null
    },
    {
      "title": "[pr-open]: 0.3.2",
      "url": "https://github.com/exaroth/i3-news/pull/5",
      "date": 1758211885,
      "author": "exaroth",
      "guid": 20032,
      "unread": true,
      "content": "",
      "contentLength": 0,
      "flags": null,
      "enclosureUrl": "",
      "enclosureMime": "",
      "commentsUrl": null
    },
    {
      "title": "[pr-closed]: 0.3.1",
      "url": "https://github.com/exaroth/i3-news/pull/4",
      "date": 1757785421,
      "author": "exaroth",
      "guid": 18782,
      "unread": true,
      "content": "## [0.3.1] 2025-13-09### Fixed<p>- Fix coalescing null values for new cache when using standard headline retrieval</p>",
      "contentLength": 111,
      "flags": null,
      "enclosureUrl": "",
      "enclosureMime": "",
      "commentsUrl": null
    },
    {
      "title": "[pr-open]: 0.3.1",
      "url": "https://github.com/exaroth/i3-news/pull/4",
      "date": 1757785301,
      "author": "exaroth",
      "guid": 18781,
      "unread": true,
      "content": "## [0.3.1] 2025-13-09### Fixed<p>- Fix coalescing null values for new cache when using standard headline retrieval</p>",
      "contentLength": 111,
      "flags": null,
      "enclosureUrl": "",
      "enclosureMime": "",
      "commentsUrl": null
    },
    {
      "title": "[pr-closed]: 0.3.0",
      "url": "https://github.com/exaroth/i3-news/pull/3",
      "date": 1757781400,
      "author": "exaroth",
      "guid": 18780,
      "unread": true,
      "content": "<article>## [0.3.0] 2025-13-09- Add --random and --latest options for headline retrieval</article>",
      "contentLength": 79,
      "flags": null,
      "enclosureUrl": "",
      "enclosureMime": "",
      "commentsUrl": null
    },
    {
      "title": "[pr-open]: 0.3.0",
      "url": "https://github.com/exaroth/i3-news/pull/3",
      "date": 1757781225,
      "author": "exaroth",
      "guid": 18779,
      "unread": true,
      "content": "<article>## [0.3.0] 2025-13-09- Add --random and --latest options for headline retrieval</article>",
      "contentLength": 79,
      "flags": null,
      "enclosureUrl": "",
      "enclosureMime": "",
      "commentsUrl": null
    },
    {
      "title": "[pr-closed]: Feat/latest and random q",
      "url": "https://github.com/exaroth/i3-news/pull/2",
      "date": 1757777488,
      "author": "exaroth",
      "guid": 18778,
      "unread": true,
      "content": "",
      "contentLength": 0,
      "flags": null,
      "enclosureUrl": "",
      "enclosureMime": "",
      "commentsUrl": null
    },
    {
      "title": "[pr-open]: Feat/latest and random q",
      "url": "https://github.com/exaroth/i3-news/pull/2",
      "date": 1757777007,
      "author": "exaroth",
      "guid": 18777,
      "unread": true,
      "content": "",
      "contentLength": 0,
      "flags": null,
      "enclosureUrl": "",
      "enclosureMime": "",
      "commentsUrl": null
    },
    {
      "title": "[pr-closed]: 0.2.1",
      "url": "https://github.com/exaroth/i3-news/pull/1",
      "date": 1757696553,
      "author": "exaroth",
      "guid": 18609,
      "unread": true,
      "content": "## [0.2.1] 2025-12-09### Changed<p>- Refactor setting read_no for newest articles</p>- Vacuum cache during feed reload- Fix install path in installation scripts",
      "contentLength": 153,
      "flags": null,
      "enclosureUrl": "",
      "enclosureMime": "",
      "commentsUrl": null
    },
    {
      "title": "[pr-open]: 0.2.1",
      "url": "https://github.com/exaroth/i3-news/pull/1",
      "date": 1757696346,
      "author": "exaroth",
      "guid": 18608,
      "unread": true,
      "content": "## [0.2.1] 2025-12-09### Changed<p>- Refactor setting read_no for newest articles</p>- Vacuum cache during feed reload- Fix install path in installation scripts",
      "contentLength": 153,
      "flags": null,
      "enclosureUrl": "",
      "enclosureMime": "",
      "commentsUrl": null
    }
  ],
  "tags": []
}